<?xml version="1.0" encoding="UTF-8" ?>
<!DOCTYPE mapper PUBLIC "-//mybatis.org//DTD Mapper 3.0//EN" "http://mybatis.org/dtd/mybatis-3-mapper.dtd" >
<mapper namespace="org.lemonPig.os.core.mapper.UserPOJOMapper" >
  <resultMap id="BaseResultMap" type="org.lemonPig.os.core.pojo.UserPOJO" >
    <!--
      WARNING - @mbggenerated
      This element is automatically generated by MyBatis Generator, do not modify.
      This element was generated on Sun May 24 19:46:56 GMT+08:00 2015.
    -->
    <id column="user_id" property="id" jdbcType="BIGINT" />
    <result column="user_userName" property="userName" jdbcType="VARCHAR" />
    <result column="user_passWord" property="passWord" jdbcType="VARCHAR" />
    <result column="user_status" property="status" jdbcType="INTEGER" />
    <result column="user_salt" property="salt" jdbcType="VARCHAR" />
    <result column="user_tel" property="tel" jdbcType="VARCHAR" />
    <result column="user_mail" property="mail" jdbcType="VARCHAR" />
  </resultMap>
  <sql id="Example_Where_Clause" >
    <!--
      WARNING - @mbggenerated
      This element is automatically generated by MyBatis Generator, do not modify.
      This element was generated on Sun May 24 19:46:56 GMT+08:00 2015.
    -->
    <where >
      <foreach collection="oredCriteria" item="criteria" separator="or" >
        <if test="criteria.valid" >
          <trim prefix="(" suffix=")" prefixOverrides="and" >
            <foreach collection="criteria.criteria" item="criterion" >
              <choose >
                <when test="criterion.noValue" >
                  and ${criterion.condition}
                </when>
                <when test="criterion.singleValue" >
                  and ${criterion.condition} #{criterion.value}
                </when>
                <when test="criterion.betweenValue" >
                  and ${criterion.condition} #{criterion.value} and #{criterion.secondValue}
                </when>
                <when test="criterion.listValue" >
                  and ${criterion.condition}
                  <foreach collection="criterion.value" item="listItem" open="(" close=")" separator="," >
                    #{listItem}
                  </foreach>
                </when>
              </choose>
            </foreach>
          </trim>
        </if>
      </foreach>
    </where>
  </sql>
  <sql id="Update_By_Example_Where_Clause" >
    <!--
      WARNING - @mbggenerated
      This element is automatically generated by MyBatis Generator, do not modify.
      This element was generated on Sun May 24 19:46:56 GMT+08:00 2015.
    -->
    <where >
      <foreach collection="example.oredCriteria" item="criteria" separator="or" >
        <if test="criteria.valid" >
          <trim prefix="(" suffix=")" prefixOverrides="and" >
            <foreach collection="criteria.criteria" item="criterion" >
              <choose >
                <when test="criterion.noValue" >
                  and ${criterion.condition}
                </when>
                <when test="criterion.singleValue" >
                  and ${criterion.condition} #{criterion.value}
                </when>
                <when test="criterion.betweenValue" >
                  and ${criterion.condition} #{criterion.value} and #{criterion.secondValue}
                </when>
                <when test="criterion.listValue" >
                  and ${criterion.condition}
                  <foreach collection="criterion.value" item="listItem" open="(" close=")" separator="," >
                    #{listItem}
                  </foreach>
                </when>
              </choose>
            </foreach>
          </trim>
        </if>
      </foreach>
    </where>
  </sql>
  <sql id="Base_Column_List" >
    <!--
      WARNING - @mbggenerated
      This element is automatically generated by MyBatis Generator, do not modify.
      This element was generated on Sun May 24 19:46:56 GMT+08:00 2015.
    -->
    user.id as user_id, user.userName as user_userName, user.passWord as user_passWord, 
    user.status as user_status, user.salt as user_salt, user.tel as user_tel, user.mail as user_mail
  </sql>
  <select id="selectByExample" resultMap="BaseResultMap" parameterType="org.lemonPig.os.core.pojo.UserPOJOExample" >
    <!--
      WARNING - @mbggenerated
      This element is automatically generated by MyBatis Generator, do not modify.
      This element was generated on Sun May 24 19:46:56 GMT+08:00 2015.
    -->
    select
    <if test="distinct" >
      distinct
    </if>
    <include refid="Base_Column_List" />
    from user user
    <if test="_parameter != null" >
      <include refid="Example_Where_Clause" />
    </if>
    <if test="orderByClause != null" >
      order by ${orderByClause}
    </if>
  </select>
  <select id="selectByPrimaryKey" resultMap="BaseResultMap" parameterType="java.lang.Long" >
    <!--
      WARNING - @mbggenerated
      This element is automatically generated by MyBatis Generator, do not modify.
      This element was generated on Sun May 24 19:46:56 GMT+08:00 2015.
    -->
    select 
    <include refid="Base_Column_List" />
    from user user
    where user.id = #{id,jdbcType=BIGINT}
  </select>
  <delete id="deleteByPrimaryKey" parameterType="java.lang.Long" >
    <!--
      WARNING - @mbggenerated
      This element is automatically generated by MyBatis Generator, do not modify.
      This element was generated on Sun May 24 19:46:56 GMT+08:00 2015.
    -->
    delete from user
    where id = #{id,jdbcType=BIGINT}
  </delete>
  <delete id="deleteByExample" parameterType="org.lemonPig.os.core.pojo.UserPOJOExample" >
    <!--
      WARNING - @mbggenerated
      This element is automatically generated by MyBatis Generator, do not modify.
      This element was generated on Sun May 24 19:46:56 GMT+08:00 2015.
    -->
    delete from user user
    <if test="_parameter != null" >
      <include refid="Example_Where_Clause" />
    </if>
  </delete>
  <insert id="insert" parameterType="org.lemonPig.os.core.pojo.UserPOJO" >
    <!--
      WARNING - @mbggenerated
      This element is automatically generated by MyBatis Generator, do not modify.
      This element was generated on Sun May 24 19:46:56 GMT+08:00 2015.
    -->
    insert into user (userName, passWord, status, 
      salt, tel, mail)
    values (#{userName,jdbcType=VARCHAR}, #{passWord,jdbcType=VARCHAR}, #{status,jdbcType=INTEGER}, 
      #{salt,jdbcType=VARCHAR}, #{tel,jdbcType=VARCHAR}, #{mail,jdbcType=VARCHAR})
    <selectKey resultType="java.lang.Long" keyProperty="id" >
      SELECT LAST_INSERT_ID()
    </selectKey>
  </insert>
  <insert id="insertSelective" parameterType="org.lemonPig.os.core.pojo.UserPOJO" >
    <!--
      WARNING - @mbggenerated
      This element is automatically generated by MyBatis Generator, do not modify.
      This element was generated on Sun May 24 19:46:56 GMT+08:00 2015.
    -->
    insert into user
    <trim prefix="(" suffix=")" suffixOverrides="," >
      <if test="userName != null" >
        userName,
      </if>
      <if test="passWord != null" >
        passWord,
      </if>
      <if test="status != null" >
        status,
      </if>
      <if test="salt != null" >
        salt,
      </if>
      <if test="tel != null" >
        tel,
      </if>
      <if test="mail != null" >
        mail,
      </if>
    </trim>
    <trim prefix="values (" suffix=")" suffixOverrides="," >
      <if test="userName != null" >
        #{userName,jdbcType=VARCHAR},
      </if>
      <if test="passWord != null" >
        #{passWord,jdbcType=VARCHAR},
      </if>
      <if test="status != null" >
        #{status,jdbcType=INTEGER},
      </if>
      <if test="salt != null" >
        #{salt,jdbcType=VARCHAR},
      </if>
      <if test="tel != null" >
        #{tel,jdbcType=VARCHAR},
      </if>
      <if test="mail != null" >
        #{mail,jdbcType=VARCHAR},
      </if>
    </trim>
    <selectKey resultType="java.lang.Long" keyProperty="id" >
      SELECT LAST_INSERT_ID()
    </selectKey>
  </insert>
  <select id="countByExample" parameterType="org.lemonPig.os.core.pojo.UserPOJOExample" resultType="java.lang.Integer" >
    <!--
      WARNING - @mbggenerated
      This element is automatically generated by MyBatis Generator, do not modify.
      This element was generated on Sun May 24 19:46:56 GMT+08:00 2015.
    -->
    select count(*) from user user
    <if test="_parameter != null" >
      <include refid="Example_Where_Clause" />
    </if>
  </select>
  <update id="updateByExampleSelective" parameterType="map" >
    <!--
      WARNING - @mbggenerated
      This element is automatically generated by MyBatis Generator, do not modify.
      This element was generated on Sun May 24 19:46:56 GMT+08:00 2015.
    -->
    update user user
    <set >
      <if test="record.id != null" >
        user.id = #{record.id,jdbcType=BIGINT},
      </if>
      <if test="record.userName != null" >
        user.userName = #{record.userName,jdbcType=VARCHAR},
      </if>
      <if test="record.passWord != null" >
        user.passWord = #{record.passWord,jdbcType=VARCHAR},
      </if>
      <if test="record.status != null" >
        user.status = #{record.status,jdbcType=INTEGER},
      </if>
      <if test="record.salt != null" >
        user.salt = #{record.salt,jdbcType=VARCHAR},
      </if>
      <if test="record.tel != null" >
        user.tel = #{record.tel,jdbcType=VARCHAR},
      </if>
      <if test="record.mail != null" >
        user.mail = #{record.mail,jdbcType=VARCHAR},
      </if>
    </set>
    <if test="_parameter != null" >
      <include refid="Update_By_Example_Where_Clause" />
    </if>
  </update>
  <update id="updateByExample" parameterType="map" >
    <!--
      WARNING - @mbggenerated
      This element is automatically generated by MyBatis Generator, do not modify.
      This element was generated on Sun May 24 19:46:56 GMT+08:00 2015.
    -->
    update user user
    set user.id = #{record.id,jdbcType=BIGINT},
      user.userName = #{record.userName,jdbcType=VARCHAR},
      user.passWord = #{record.passWord,jdbcType=VARCHAR},
      user.status = #{record.status,jdbcType=INTEGER},
      user.salt = #{record.salt,jdbcType=VARCHAR},
      user.tel = #{record.tel,jdbcType=VARCHAR},
      user.mail = #{record.mail,jdbcType=VARCHAR}
    <if test="_parameter != null" >
      <include refid="Update_By_Example_Where_Clause" />
    </if>
  </update>
  <update id="updateByPrimaryKeySelective" parameterType="org.lemonPig.os.core.pojo.UserPOJO" >
    <!--
      WARNING - @mbggenerated
      This element is automatically generated by MyBatis Generator, do not modify.
      This element was generated on Sun May 24 19:46:56 GMT+08:00 2015.
    -->
    update user
    <set >
      <if test="userName != null" >
        userName = #{userName,jdbcType=VARCHAR},
      </if>
      <if test="passWord != null" >
        passWord = #{passWord,jdbcType=VARCHAR},
      </if>
      <if test="status != null" >
        status = #{status,jdbcType=INTEGER},
      </if>
      <if test="salt != null" >
        salt = #{salt,jdbcType=VARCHAR},
      </if>
      <if test="tel != null" >
        tel = #{tel,jdbcType=VARCHAR},
      </if>
      <if test="mail != null" >
        mail = #{mail,jdbcType=VARCHAR},
      </if>
    </set>
    where id = #{id,jdbcType=BIGINT}
  </update>
  <update id="updateByPrimaryKey" parameterType="org.lemonPig.os.core.pojo.UserPOJO" >
    <!--
      WARNING - @mbggenerated
      This element is automatically generated by MyBatis Generator, do not modify.
      This element was generated on Sun May 24 19:46:56 GMT+08:00 2015.
    -->
    update user
    set userName = #{userName,jdbcType=VARCHAR},
      passWord = #{passWord,jdbcType=VARCHAR},
      status = #{status,jdbcType=INTEGER},
      salt = #{salt,jdbcType=VARCHAR},
      tel = #{tel,jdbcType=VARCHAR},
      mail = #{mail,jdbcType=VARCHAR}
    where id = #{id,jdbcType=BIGINT}
  </update>
</mapper>